cert_report/__init__.py
cert_report/certs.py
ops_py_cert_report-5.0.3.dist-info/LICENSE
ops_py_cert_report-5.0.3.dist-info/METADATA
ops_py_cert_report-5.0.3.dist-info/WHEEL
ops_py_cert_report-5.0.3.dist-info/top_level.txt
ops_py_cert_report-5.0.3.dist-info/RECORD
