Metadata-Version: 2.1
Name: ops-py-cert-report
Version: 5.0.3
Summary: Output a Cert expire report
License: MIT License
License-File: LICENSE
Requires-Dist: pip ==24.3.1
Requires-Dist: setuptools ==75.5.0
Requires-Dist: wheel ==0.45.0
